db_connector_app/__init__.py
db_connector_app/connection.py
db_connector_app-0.1.dist-info/LICENSE
db_connector_app-0.1.dist-info/METADATA
db_connector_app-0.1.dist-info/WHEEL
db_connector_app-0.1.dist-info/top_level.txt
db_connector_app-0.1.dist-info/RECORD
