Metadata-Version: 2.1
Name: db_connector_app
Version: 0.1
Summary: A package for handling database connections across different databases
Home-page: https://github.com/IBZBS/database_connector.git
Author: periyanayagam
Author-email: periyanayagam.anthonysamy@itbeezone.in
Classifier: Programming Language :: Python :: 3
Classifier: License :: OSI Approved :: MIT License
Classifier: Operating System :: OS Independent
Requires-Python: >=3.6
License-File: LICENSE
Requires-Dist: sqlalchemy
Requires-Dist: pymongo
Requires-Dist: cassandra-driver
Requires-Dist: redis
Requires-Dist: couchdb
Requires-Dist: boto3
Requires-Dist: neo4j
Requires-Dist: python-dotenv
